imnn/__init__.py
imnn/imnn/__init__.py
imnn/imnn/_aggregated_imnn.py
imnn/imnn/_imnn.py
imnn/imnn/_imnn_test.py
imnn/imnn/aggregated_gradient_imnn.py
imnn/imnn/aggregated_gradient_imnn_test.py
imnn/imnn/aggregated_numerical_gradient_imnn.py
imnn/imnn/aggregated_numerical_gradient_imnn_test.py
imnn/imnn/aggregated_simulator_imnn.py
imnn/imnn/aggregated_simulator_imnn_test.py
imnn/imnn/dataset_gradient_imnn.py
imnn/imnn/dataset_gradient_imnn_test.py
imnn/imnn/dataset_numerical_gradient_imnn.py
imnn/imnn/dataset_numerical_gradient_imnn_test.py
imnn/imnn/gradient_imnn.py
imnn/imnn/gradient_imnn_test.py
imnn/imnn/imnn.py
imnn/imnn/imnn_test.py
imnn/imnn/numerical_gradient_imnn.py
imnn/imnn/numerical_gradient_imnn_test.py
imnn/imnn/simulator_imnn.py
imnn/imnn/simulator_imnn_test.py
imnn/lfi/__init__.py
imnn/lfi/approximate_bayesian_computation.py
imnn/lfi/gaussian_approximation.py
imnn/lfi/lfi.py
imnn/lfi/population_monte_carlo.py
imnn/utils/__init__.py
imnn/utils/container.py
imnn/utils/jac.py
imnn/utils/progress_bar.py
imnn/utils/tfrecords.py
imnn/utils/utils.py
IMNN-0.3.2.dist-info/LICENSE
IMNN-0.3.2.dist-info/METADATA
IMNN-0.3.2.dist-info/WHEEL
IMNN-0.3.2.dist-info/top_level.txt
IMNN-0.3.2.dist-info/RECORD
