Metadata-Version: 2.1
Name: IMNN
Version: 0.3.2
Summary: Using neural networks to extract sufficient statistics from         data by maximising the Fisher information
Home-page: https://bitbucket.org/tomcharnock/imnn.git
Author: Tom Charnock
Author-email: charnock@iap.fr
License: UNKNOWN
Platform: UNKNOWN
Classifier: Programming Language :: Python :: 3
Classifier: License :: OSI Approved :: MIT License
Classifier: Operating System :: OS Independent
Requires-Python: >=3.6
License-File: LICENSE
Requires-Dist: jax (>=0.2.24)
Requires-Dist: jaxlib (>=0.1.73)
Requires-Dist: tensorflow
Requires-Dist: tqdm (>=4.48.2)
Requires-Dist: tensorflow-probability[jax]
Requires-Dist: numpy
Requires-Dist: scipy
Requires-Dist: matplotlib
